odoo/addons/product_print_category/README.rst
odoo/addons/product_print_category/__init__.py
odoo/addons/product_print_category/__manifest__.py
odoo/addons/product_print_category/data/report_paperformat.xml
odoo/addons/product_print_category/demo/product_print_category.xml
odoo/addons/product_print_category/demo/product_product.xml
odoo/addons/product_print_category/demo/qweb_template.xml
odoo/addons/product_print_category/demo/res_groups.xml
odoo/addons/product_print_category/i18n/fr.po
odoo/addons/product_print_category/models/__init__.py
odoo/addons/product_print_category/models/product_print_category.py
odoo/addons/product_print_category/models/product_print_category_mixin.py
odoo/addons/product_print_category/models/product_product.py
odoo/addons/product_print_category/models/product_template.py
odoo/addons/product_print_category/models/res_company.py
odoo/addons/product_print_category/readme/CONTRIBUTORS.rst
odoo/addons/product_print_category/readme/DESCRIPTION.rst
odoo/addons/product_print_category/readme/USAGE.rst
odoo/addons/product_print_category/report/__init__.py
odoo/addons/product_print_category/report/ir_actions_report.xml
odoo/addons/product_print_category/report/report_pricetag.py
odoo/addons/product_print_category/report/report_pricetag.xml
odoo/addons/product_print_category/security/ir.model.access.csv
odoo/addons/product_print_category/security/ir_module_category.xml
odoo/addons/product_print_category/security/res_groups.xml
odoo/addons/product_print_category/static/description/index.html
odoo/addons/product_print_category/static/description/index.png
odoo/addons/product_print_category/static/description/print_category.png
odoo/addons/product_print_category/static/description/print_products.png
odoo/addons/product_print_category/static/description/product_print_options.png
odoo/addons/product_print_category/tests/__init__.py
odoo/addons/product_print_category/tests/test_product_print_category.py
odoo12_addon_product_print_category-12.0.1.1.7.dist-info/METADATA
odoo12_addon_product_print_category-12.0.1.1.7.dist-info/WHEEL
odoo12_addon_product_print_category-12.0.1.1.7.dist-info/top_level.txt
odoo12_addon_product_print_category-12.0.1.1.7.dist-info/RECORD
