Metadata-Version: 2.1
Name: odoo12-addon-product-print-category
Version: 12.0.1.1.7
Summary: Automate products print, when data has changed
Home-page: https://github.com/grap/grap-odoo-incubator
Author: GRAP, La Louve, Coop IT Easy SCRLfs, Odoo Community Association (OCA)
Author-email: support@odoo-community.org
License: AGPL-3
Platform: UNKNOWN
Classifier: Programming Language :: Python
Classifier: Framework :: Odoo
Classifier: Framework :: Odoo :: 12.0
Classifier: License :: OSI Approved :: GNU Affero General Public License v3
Requires-Python: >=3.5
Requires-Dist: odoo (<12.1dev,>=12.0a)
